trac_WorkflowNotificationPlugin-0.6.dist-info/METADATA
trac_WorkflowNotificationPlugin-0.6.dist-info/RECORD
trac_WorkflowNotificationPlugin-0.6.dist-info/WHEEL
trac_WorkflowNotificationPlugin-0.6.dist-info/entry_points.txt
trac_WorkflowNotificationPlugin-0.6.dist-info/top_level.txt
workflow_notification/__init__.py
workflow_notification/templates/ticket_notify_workflow_email.txt
workflow_notification/templates/workflow_notification_admin.html
workflow_notification/templates/workflow_notification_rule_admin.html
