Metadata-Version: 2.1
Name: trac-WorkflowNotificationPlugin
Version: 0.6
Summary: Configurable notifications for trac tickets tied to workflow actions
Home-page: https://trac-hacks.org/wiki/WorkflowNotificationPlugin
Author: Ethan Jucovy
Author-email: ejucovy@gmail.com
License: BSD
Platform: UNKNOWN
